qmemetic_ai/__init__.py
qmemetic_ai/cli.py
qmemetic_ai/cognitive/__init__.py
qmemetic_ai/cognitive/models.py
qmemetic_ai/core/__init__.py
qmemetic_ai/core/engine.py
qmemetic_ai/core/entanglement.py
qmemetic_ai/core/evolution.py
qmemetic_ai/core/meme.py
qmemetic_ai/federation/__init__.py
qmemetic_ai/federation/client.py
qmemetic_ai/licensing/__init__.py
qmemetic_ai/licensing/manager.py
qmemetic_ai/utils/__init__.py
qmemetic_ai/utils/persistence.py
qmemetic_ai/utils/security.py
qmemetic_ai/visualization/__init__.py
qmemetic_ai/visualization/noosphere.py
qmemetic_ai-0.1.0.dist-info/METADATA
qmemetic_ai-0.1.0.dist-info/WHEEL
qmemetic_ai-0.1.0.dist-info/entry_points.txt
qmemetic_ai-0.1.0.dist-info/top_level.txt
qmemetic_ai-0.1.0.dist-info/RECORD
