Metadata-Version: 2.4
Name: qmemetic-ai
Version: 0.1.0
Summary: Quantum-inspired AI system for evolving, mutating, and entangling memes across users, systems, and timelines
Home-page: https://github.com/yourusername/qmemetic
Author: Your Name
Author-email: Krishna Bajpai <bajpaikrishna715@gmail.com>
License: QuantumMeta License
Project-URL: Homepage, https://github.com/krish567366/Q-Memetic-AI
Project-URL: Documentation, https://krish567366.github.io/Q-Memetic-AI/
Project-URL: Repository, https://github.com/krish567366/Q-Memetic-AI
Project-URL: Issues, https://github.com/krish567366/Q-Memetic-AI/issues
Keywords: quantum,memetics,ai,evolution,entanglement,federation
Classifier: Development Status :: 4 - Beta
Classifier: Intended Audience :: Developers
Classifier: Intended Audience :: Science/Research
Classifier: License :: Other/Proprietary License
Classifier: Operating System :: OS Independent
Classifier: Programming Language :: Python :: 3
Classifier: Programming Language :: Python :: 3.9
Classifier: Programming Language :: Python :: 3.10
Classifier: Programming Language :: Python :: 3.11
Classifier: Programming Language :: Python :: 3.12
Classifier: Topic :: Scientific/Engineering :: Artificial Intelligence
Classifier: Topic :: Software Development :: Libraries :: Python Modules
Requires-Python: >=3.7
Requires-Dist: quantummeta-license>=1.0.0
Requires-Dist: transformers>=4.30.0
Requires-Dist: torch>=2.0.0
Requires-Dist: numpy>=1.24.0
Requires-Dist: networkx>=3.0
Requires-Dist: sentence-transformers>=2.2.0
Requires-Dist: openai>=1.0.0
Requires-Dist: plotly>=5.0.0
Requires-Dist: click>=8.0.0
Requires-Dist: pydantic>=2.0.0
Requires-Dist: fastapi>=0.100.0
Requires-Dist: uvicorn>=0.20.0
Requires-Dist: aiofiles>=23.0.0
Requires-Dist: cryptography>=40.0.0
Requires-Dist: scipy>=1.10.0
Requires-Dist: scikit-learn>=1.3.0
Requires-Dist: redis>=4.5.0
Requires-Dist: psutil>=5.9.0
Requires-Dist: rich>=13.0.0
Requires-Dist: typer>=0.9.0
Provides-Extra: dev
Requires-Dist: pytest>=7.0.0; extra == "dev"
Requires-Dist: pytest-asyncio>=0.21.0; extra == "dev"
Requires-Dist: pytest-cov>=4.0.0; extra == "dev"
Requires-Dist: black>=23.0.0; extra == "dev"
Requires-Dist: isort>=5.12.0; extra == "dev"
Requires-Dist: flake8>=6.0.0; extra == "dev"
Requires-Dist: mypy>=1.0.0; extra == "dev"
Requires-Dist: pre-commit>=3.0.0; extra == "dev"
Provides-Extra: docs
Requires-Dist: mkdocs>=1.5.0; extra == "docs"
Requires-Dist: mkdocs-material>=9.0.0; extra == "docs"
Requires-Dist: mkdocstrings[python]>=0.22.0; extra == "docs"
Requires-Dist: mkdocs-mermaid2-plugin>=1.0.0; extra == "docs"
Requires-Dist: mkdocs-jupyter>=0.24.0; extra == "docs"
Provides-Extra: research
Requires-Dist: jupyter>=1.0.0; extra == "research"
Requires-Dist: matplotlib>=3.7.0; extra == "research"
Requires-Dist: seaborn>=0.12.0; extra == "research"
Requires-Dist: pandas>=2.0.0; extra == "research"
Requires-Dist: notebook>=6.5.0; extra == "research"
Provides-Extra: federation
Requires-Dist: flower>=1.5.0; extra == "federation"
Requires-Dist: grpcio>=1.50.0; extra == "federation"
Requires-Dist: protobuf>=4.0.0; extra == "federation"
Provides-Extra: multimodal
Requires-Dist: diffusers>=0.20.0; extra == "multimodal"
Requires-Dist: whisper>=1.0.0; extra == "multimodal"
Requires-Dist: Pillow>=10.0.0; extra == "multimodal"
Requires-Dist: opencv-python>=4.8.0; extra == "multimodal"
Dynamic: author
Dynamic: home-page
Dynamic: requires-python
